engine_core/__init__.py
engine_core/api/__init__.py
engine_core/api/main.py
engine_core/api/routers/__init__.py
engine_core/api/routers/agents.py
engine_core/api/routers/books.py
engine_core/api/schemas/__init__.py
engine_core/api/schemas/agent_schemas.py
engine_core/api/schemas/base_schemas.py
engine_core/api/schemas/book_schemas.py
engine_core/api/schemas/enums.py
engine_core/core/__init__.py
engine_core/core/agents/__init__.py
engine_core/core/agents/agent.py
engine_core/core/agents/agent_builder.py
engine_core/core/agents/agent_config.py
engine_core/core/agents/exceptions.py
engine_core/core/agents/test.py
engine_core/core/book/__init__.py
engine_core/core/book/book.py
engine_core/core/book/book_builder.py
engine_core/core/protocols/__init__.py
engine_core/core/protocols/protocol.py
engine_core/core/protocols/protocol_builder.py
engine_core/core/protocols/protocol_parser.py
engine_core/core/teams/__init__.py
engine_core/core/teams/team.py
engine_core/core/teams/team_builder.py
engine_core/core/tools/__init__.py
engine_core/core/tools/plugins/calculator_plugin.py
engine_core/core/tools/tool.py
engine_core/core/tools/tool_builder.py
engine_core/core/tools/tool_executor.py
engine_core/core/workflows/__init__.py
engine_core/core/workflows/workflow.py
engine_core/core/workflows/workflow_builder.py
engine_core/core/workflows/workflow_engine.py
engine_core/engine_types.py
engine_core/models/__init__.py
engine_core/models/agent.py
engine_core/models/base.py
engine_core/models/book.py
engine_core/models/infrastructure.py
engine_core/models/project.py
engine_core/models/project.py.backup
engine_core/models/project.py.temp
engine_core/models/protocol.py
engine_core/models/team.py
engine_core/models/tool.py
engine_core/models/workflow.py
engine_core/services/__init__.py
engine_core/services/agent_service.py
engine_core/services/book_service.py
engine_core/services/observability_service.py
engine_core/services/protocol_service.py
engine_core/services/team_service.py
engine_core-1.0.1.dist-info/METADATA
engine_core-1.0.1.dist-info/WHEEL
engine_core-1.0.1.dist-info/licenses/LICENSE
engine_core-1.0.1.dist-info/licenses/LICENSE-COMMERCIAL
engine_core-1.0.1.dist-info/RECORD
