Metadata-Version: 2.4
Name: engine-core
Version: 1.0.1
Summary: Engine Framework Core - AI Agent Orchestration System
License: AGPL-3.0
License-File: LICENSE
License-File: LICENSE-COMMERCIAL
Keywords: ai,agents,orchestration,framework,pregel,actor-model
Author: Engine Framework Team
Author-email: engine@example.com
Requires-Python: >=3.11,<4.0
Classifier: Development Status :: 5 - Production/Stable
Classifier: Intended Audience :: Developers
Classifier: License :: OSI Approved :: GNU Affero General Public License v3
Classifier: Operating System :: OS Independent
Classifier: Programming Language :: Python :: 3
Classifier: Programming Language :: Python :: 3.11
Classifier: Programming Language :: Python :: 3.12
Classifier: Programming Language :: Python :: 3.13
Classifier: Programming Language :: Python :: 3.14
Classifier: Topic :: Scientific/Engineering :: Artificial Intelligence
Classifier: Topic :: Software Development :: Libraries :: Python Modules
Requires-Dist: aiohttp (>=3.9.0,<4.0.0)
Requires-Dist: fastapi (>=0.104.1,<0.105.0)
Requires-Dist: httpx (>=0.25.2,<0.26.0)
Requires-Dist: psutil (>=5.9.0,<6.0.0)
Requires-Dist: pydantic[email] (>=2.5.0,<3.0.0)
Requires-Dist: redis[hiredis] (>=5.0.1,<6.0.0)
Requires-Dist: sqlalchemy[asyncio] (>=2.0.0,<3.0.0)
Requires-Dist: tenacity (>=8.2.3,<9.0.0)
Requires-Dist: uvicorn[standard] (>=0.24.0,<0.25.0)
Project-URL: Homepage, https://github.com/engine-agi/engine-core
Project-URL: Repository, https://github.com/engine-agi/engine-core
